{
  "법령명": "건축법",
  "조항들": [
    {
      "조항": "제44조",
      "조문_전문": "제44조(대지와 도로의 관계) ① 건축물의 대지는 2미터 이상이 도로(자동차만의 통행에 사용되는 도로는 제외한다)에 접하여야 한다. 다만, 다음 각 호의 어느 하나에 해당하면 그러하지 아니하다. &lt;개정 2016. 1. 19.&gt;\n1. 해당 건축물의 출입에 지장이 없다고 인정되는 경우\n2. 건축물의 주변에 대통령령으로 정하는 공지가 있는 경우\n3. 「농지법」 제2조제1호나목에 따른 농막을 건축하는 경우\n② 건축물의 대지가 접하는 도로의 너비, 대지가 도로에 접하는 부분의 길이, 그 밖에 대지와 도로의 관계에 관하여 필요한 사항은 대통령령으로 정하는 바에 따른다.",
      "요약": null
    },
    {
      "조항": "제58조",
      "조문_전문": "제58조(대지 안의 공지) 건축물을 건축하는 경우에는 「국토의 계획 및 이용에 관한 법률」에 따른 용도지역ㆍ용도지구, 건축물의 용도 및 규모 등에 따라 건축선 및 인접 대지경계선으로부터 6미터 이내의 범위에서 대통령령으로 정하는 바에 따라 해당 지방자치단체의 조례로 정하는 거리 이상을 띄워야 한다. &lt;개정 2011. 5. 30.&gt;",
      "요약": null
    },
    {
      "조항": "제3조",
      "조문_전문": "제3조(적용 제외) ① 다음 각 호의 어느 하나에 해당하는 건축물에는 이 법을 적용하지 아니한다. &lt;개정 2016. 1. 19., 2019. 11. 26., 2023. 3. 21., 2023. 8. 8., 2024. 2. 6.&gt;\n1. 「문화유산의 보존 및 활용에 관한 법률」에 따른 지정문화유산이나 임시지정문화유산 또는 「자연유산의 보존 및 활용에 관한 법률」에 따라 지정된 천연기념물등이나 임시지정천연기념물, 임시지정명승, 임시지정시ㆍ도자연유산, 임시자연유산자료\n2. 철도나 궤도의 선로 부지(敷地)에 있는 다음 각 목의 시설\n가. 운전보안시설\n나. 철도 선로의 위나 아래를 가로지르는 보행시설\n다. 플랫폼\n라. 해당 철도 또는 궤도사업용 급수(給水)ㆍ급탄(給炭) 및 급유(給油) 시설\n3. 고속도로 통행료 징수시설\n4. 컨테이너를 이용한 간이창고(「산업집적활성화 및 공장설립에 관한 법률」 제2조제1호에 따른 공장의 용도로만 사용되는 건축물의 대지에 설치하는 것으로서 이동이 쉬운 것만 해당된다)\n5. 「하천법」에 따른 하천구역 내의 수문조작실\n② 「국토의 계획 및 이용에 관한 법률」에 따른 도시지역 및 같은 법 제51조제3항에 따른 지구단위계획구역(이하 “지구단위계획구역”이라 한다) 외의 지역으로서 동이나 읍(동이나 읍에 속하는 섬의 경우에는 인구가 500명 이상인 경우만 해당된다)이 아닌 지역은 제44조부터 제47조까지, 제51조 및 제57조를 적용하지 아니한다. &lt;개정 2011. 4. 14., 2014. 1. 14.&gt;\n③ 「국토의 계획 및 이용에 관한 법률」 제47조제7항에 따른 건축물이나 공작물을 도시ㆍ군계획시설로 결정된 도로의 예정지에 건축하는 경우에는 제45조부터 제47조까지의 규정을 적용하지 아니한다. &lt;개정 2011. 4. 14.&gt;",
      "요약": null
    },
    {
      "조항": "제47조",
      "조문_전문": "제47조(건축선에 따른 건축제한) ① 건축물과 담장은 건축선의 수직면(垂直面)을 넘어서는 아니 된다. 다만, 지표(地表) 아래 부분은 그러하지 아니하다.\n② 도로면으로부터 높이 4.5미터 이하에 있는 출입구, 창문, 그 밖에 이와 유사한 구조물은 열고 닫을 때 건축선의 수직면을 넘지 아니하는 구조로 하여야 한다.",
      "요약": null
    },
    {
      "조항": "제46조",
      "조문_전문": "제46조(건축선의 지정) ① 도로와 접한 부분에 건축물을 건축할 수 있는 선[이하 “건축선(建築線)”이라 한다]은 대지와 도로의 경계선으로 한다. 다만, 제2조제1항제11호에 따른 소요 너비에 못 미치는 너비의 도로인 경우에는 그 중심선으로부터 그 소요 너비의 2분의 1의 수평거리만큼 물러난 선을 건축선으로 하되, 그 도로의 반대쪽에 경사지, 하천, 철도, 선로부지, 그 밖에 이와 유사한 것이 있는 경우에는 그 경사지 등이 있는 쪽의 도로경계선에서 소요 너비에 해당하는 수평거리의 선을 건축선으로 하며, 도로의 모퉁이에서는 대통령령으로 정하는 선을 건축선으로 한다.\n② 특별자치시장ㆍ특별자치도지사 또는 시장ㆍ군수ㆍ구청장은 시가지 안에서 건축물의 위치나 환경을 정비하기 위하여 필요하다고 인정하면 제1항에도 불구하고 대통령령으로 정하는 범위에서 건축선을 따로 지정할 수 있다. &lt;개정 2014. 1. 14.&gt;\n③ 특별자치시장ㆍ특별자치도지사 또는 시장ㆍ군수ㆍ구청장은 제2항에 따라 건축선을 지정하면 지체 없이 이를 고시하여야 한다. &lt;개정 2014. 1. 14.&gt;",
      "요약": null
    }
  ]
}